markdown_spa/__init__.py
markdown_spa/__main__.py
markdown_spa/config.py
markdown_spa/extensions/__init__.py
markdown_spa/extensions/extension.py
markdown_spa/extensions/SASS/SASS.py
markdown_spa/extensions/SASS/__init__.py
markdown_spa/extensions/SASS/main.scss
markdown_spa/extensions/Sitemap/Sitemap.py
markdown_spa/extensions/Sitemap/__init__.py
markdown_spa/extensions/Sitemap/robots.txt
markdown_spa/extensions/Sitemap/sitemap.xml
markdown_spa/extensions/Tailwind/Tailwind.py
markdown_spa/extensions/Tailwind/__init__.py
markdown_spa/extensions/Tailwind/tailwind.config.js
markdown_spa/generator/__init__.py
markdown_spa/generator/cli.py
markdown_spa/generator/generator.py
Markdown_SPA-3.0.3.dist-info/LICENSE
Markdown_SPA-3.0.3.dist-info/METADATA
Markdown_SPA-3.0.3.dist-info/WHEEL
Markdown_SPA-3.0.3.dist-info/entry_points.txt
Markdown_SPA-3.0.3.dist-info/top_level.txt
Markdown_SPA-3.0.3.dist-info/RECORD
