Metadata-Version: 2.1
Name: Markdown-SPA
Version: 3.0.3
Summary: A static site generator for Markdown files.
Author: MrSpaar
License: MIT License
Project-URL: Documentation, https://mrspaar.github.io/Markdown-SPA/
Project-URL: Homepage, https://github.com/MrSpaar/Markdown-SPA
Project-URL: Issues, https://github.com/MrSpaar/Markdown-SPA/issues
Keywords: markdown,SPA,SSG,CLI
Classifier: Development Status :: 5 - Production/Stable
Classifier: Environment :: Console
Classifier: Environment :: Web Environment
Classifier: Intended Audience :: Developers
Classifier: License :: OSI Approved :: MIT License
Classifier: Operating System :: OS Independent
Classifier: Programming Language :: Python :: 3
Classifier: Programming Language :: Python :: 3 :: Only
Classifier: Programming Language :: Python :: 3.8
Classifier: Programming Language :: Python :: 3.9
Classifier: Programming Language :: Python :: 3.10
Classifier: Programming Language :: Python :: 3.11
Classifier: Programming Language :: Python :: 3.12
Classifier: Topic :: Utilities
Classifier: Topic :: Documentation
Classifier: Topic :: Software Development :: Documentation
Classifier: Topic :: Software Development :: Build Tools
Classifier: Topic :: Text Processing :: Markup :: HTML
Classifier: Topic :: Internet :: WWW/HTTP :: Site Management
Requires-Python: >=3.8
License-File: LICENSE
Requires-Dist: markdown
Requires-Dist: jinja2
Requires-Dist: pygments
Requires-Dist: click
Requires-Dist: requests
Requires-Dist: importlib-metadata
